reflex_github_badge/__init__.py
reflex_github_badge/github_badge.py
reflex_github_badge-0.0.3.dist-info/METADATA
reflex_github_badge-0.0.3.dist-info/WHEEL
reflex_github_badge-0.0.3.dist-info/top_level.txt
reflex_github_badge-0.0.3.dist-info/RECORD
